Metadata-Version: 2.1
Name: covid19-api
Version: 1.0
Summary: coroapi is fast and up-to-date Covid-19 API
Home-page: https://github.com/r0ei/coroapi
Author: Roi Levi
Author-email: roeil4939@gmail.com
License: UNKNOWN
Platform: UNKNOWN
